navigation_analytics/__init__.py
navigation_analytics/navigation_data.py
navigation_analytics-0.0.1.dist-info/LICENSE
navigation_analytics-0.0.1.dist-info/METADATA
navigation_analytics-0.0.1.dist-info/WHEEL
navigation_analytics-0.0.1.dist-info/top_level.txt
navigation_analytics-0.0.1.dist-info/RECORD
