Metadata-Version: 2.1
Name: navigation-analytics
Version: 0.0.1
Summary: Toolkit that creates portable objects specialized on analyzing web navigation data.
Home-page: https://github.com/mielgosez/navigation_analytics
Author: Jose Mielgo
Author-email: mielgosez@gmail.com
License: UNKNOWN
Project-URL: Bug Tracker, https://github.com/mielgosez/navigation_analytics/issues
Platform: UNKNOWN
Classifier: Programming Language :: Python :: 3
Classifier: License :: OSI Approved :: MIT License
Classifier: Operating System :: OS Independent
Requires-Python: >=3.6
License-File: LICENSE
Requires-Dist: pandas
Requires-Dist: numpy
